mermaid_ascii/__init__.py
mermaid_ascii/class_parse.py
mermaid_ascii/cli.py
mermaid_ascii/layout.py
mermaid_ascii/model.py
mermaid_ascii/parse.py
mermaid_ascii/py.typed
mermaid_ascii/render.py
mermaid_ascii/sequence_model.py
mermaid_ascii/sequence_parse.py
mermaid_ascii/sequence_render.py
mermaid_ascii/state_parse.py
mermaid_ascii_diagrams-0.1.1.dist-info/METADATA
mermaid_ascii_diagrams-0.1.1.dist-info/WHEEL
mermaid_ascii_diagrams-0.1.1.dist-info/entry_points.txt
mermaid_ascii_diagrams-0.1.1.dist-info/top_level.txt
mermaid_ascii_diagrams-0.1.1.dist-info/RECORD
