Metadata-Version: 2.4
Name: mermaid-ascii-diagrams
Version: 0.1.1
Summary: Render Mermaid diagrams to ASCII/Unicode art
Author: Th3S3cr3tAg3nt
License: MIT
Project-URL: Homepage, https://github.com/Th3S3cr3tAg3nt/mermaid-ascii-diagrams
Project-URL: Issues, https://github.com/Th3S3cr3tAg3nt/mermaid-ascii-diagrams/issues
Keywords: mermaid,ascii,unicode,diagram,markdown
Classifier: Development Status :: 3 - Alpha
Classifier: Intended Audience :: Developers
Classifier: License :: OSI Approved :: MIT License
Classifier: Programming Language :: Python :: 3
Classifier: Programming Language :: Python :: 3 :: Only
Classifier: Programming Language :: Python :: 3.10
Classifier: Programming Language :: Python :: 3.11
Classifier: Programming Language :: Python :: 3.12
Classifier: Programming Language :: Python :: 3.13
Classifier: Topic :: Software Development :: Documentation
Classifier: Topic :: Text Processing :: Markup
Requires-Python: >=3.10
Provides-Extra: dev
Requires-Dist: pytest>=7; extra == "dev"
Requires-Dist: ruff>=0.5; extra == "dev"
Requires-Dist: build>=1; extra == "dev"
Requires-Dist: twine>=5; extra == "dev"
